{
  "build": {
    "content": [
      {
        "files": [
          "**/*.md",
          "**/*.yml"
        ],
        "exclude": [
          "**/obj/**",
          "vs-mobile-center-docs/**",
          "**/includes/**"
        ]
      }
    ],
    "resource": [
      {
        "files": [
          "**/*.png",
          "**/*.jpg"
        ],
        "exclude": [
          "**/obj/**",
          "vs-mobile-center-docs/**",
          "**/includes/**"
        ]
      }
    ],
    "overwrite": [],
    "externalReference": [],
    "globalMetadata": {
      "breadcrumb_path": "~/general/toc.json"
    },
    "fileMetadata": {},
    "template": [],
    "dest": "vs-mobile-center-docs"
  }
}
